clincher.py
clincher-1.0.dist-info/entry_points.txt
clincher-1.0.dist-info/LICENSE
clincher-1.0.dist-info/WHEEL
clincher-1.0.dist-info/METADATA
clincher-1.0.dist-info/RECORD
