Metadata-Version: 2.1
Name: clincher
Version: 1.0
Summary: Clincher is a tool for checking that all the commits in a git repo are signed
Home-page: https://github.com/lshift/clincher
License: UNKNOWN
Author: Tom Parker-Shemilt
Author-email: palfrey@tevp.net
Requires-Python: >=3.6,<4
Classifier: License :: OSI Approved :: GNU Affero General Public License v3
Classifier: Intended Audience :: Developers
Classifier: Programming Language :: Python :: 3
Classifier: Topic :: Software Development :: Version Control :: Git
Requires-Dist: GitPython
Requires-Dist: dateparser
Provides-Extra: .none
